lk_typer_packaging_tutor/__init__.py
lk_typer_packaging_tutor/__main__.py
lk_typer_packaging_tutor/main.py
lk_typer_packaging_tutor-0.2.0.dist-info/entry_points.txt
lk_typer_packaging_tutor-0.2.0.dist-info/METADATA
lk_typer_packaging_tutor-0.2.0.dist-info/WHEEL
lk_typer_packaging_tutor-0.2.0.dist-info/RECORD
