Metadata-Version: 2.1
Name: lk-typer-packaging-tutor
Version: 0.2.0
Summary: 
Author: Lukasz A. Kadlubowski
Author-email: lukasz.kadlubowski@gmail.com
Requires-Python: >=3.12,<4.0
Classifier: Programming Language :: Python :: 3
Classifier: Programming Language :: Python :: 3.12
Requires-Dist: typer (>=0.12.5,<0.13.0)
